arithmetica.cp310-win_amd64.pyd
arithmetica_py-1.0.226.data/data/src/python-module/libarithmetica.a
arithmetica_py-1.0.226.data/data/src/python-module/libbasic_math_operations.a
arithmetica_py-1.0.226.data/data/src/python-module/version.txt
src/python-module/module.c
arithmetica_py-1.0.226.dist-info/LICENSE
arithmetica_py-1.0.226.dist-info/METADATA
arithmetica_py-1.0.226.dist-info/WHEEL
arithmetica_py-1.0.226.dist-info/top_level.txt
arithmetica_py-1.0.226.dist-info/RECORD
