Metadata-Version: 2.1
Name: arithmetica-py
Version: 1.0.226
Summary: General purpose math library with primarily arithmetic functions.
Author: avighnac
Author-email: avighnakc@gmail.com
License-File: LICENSE
